srb/__init__.py
srb/__main__.py
srb/py.typed
srb/_typing/__init__.py
srb/_typing/cfg.py
srb/_typing/enum.py
srb/_typing/step_return.py
srb/assets/__init__.py
srb/assets/object/__init__.py
srb/assets/object/beneficiation_unit.py
srb/assets/object/bolt_and_nut.py
srb/assets/object/juggling_ball.py
srb/assets/object/peg_in_hole.py
srb/assets/object/rock.py
srb/assets/object/sample.py
srb/assets/object/shape.py
srb/assets/object/solar_panel.py
srb/assets/object/light/__init__.py
srb/assets/object/payload/__init__.py
srb/assets/object/payload/cargo_bay.py
srb/assets/object/pedestal/__init__.py
srb/assets/object/pedestal/industrial.py
srb/assets/object/tool/__init__.py
srb/assets/object/tool/allegro_hand.py
srb/assets/object/tool/franka_hand.py
srb/assets/object/tool/kinova_gripper.py
srb/assets/object/tool/robotiq.py
srb/assets/object/tool/scoop.py
srb/assets/object/tool/screwdriver.py
srb/assets/object/tool/shadow_hand.py
srb/assets/object/tool/so_arm100.py
srb/assets/robot/__init__.py
srb/assets/robot/manipulation/__init__.py
srb/assets/robot/manipulation/canadarm3.py
srb/assets/robot/manipulation/franka.py
srb/assets/robot/manipulation/kinova.py
srb/assets/robot/manipulation/so_arm100.py
srb/assets/robot/manipulation/unitree.py
srb/assets/robot/manipulation/universal_robots.py
srb/assets/robot/mobile/__init__.py
srb/assets/robot/mobile/anymal.py
srb/assets/robot/mobile/cassie.py
srb/assets/robot/mobile/crazyflie.py
srb/assets/robot/mobile/ingenuity.py
srb/assets/robot/mobile/lander.py
srb/assets/robot/mobile/leo_rover.py
srb/assets/robot/mobile/mars_rover.py
srb/assets/robot/mobile/perseverance.py
srb/assets/robot/mobile/pragyan.py
srb/assets/robot/mobile/spacecraft.py
srb/assets/robot/mobile/spot.py
srb/assets/robot/mobile/unitree.py
srb/assets/robot/mobile_manipulation/__init__.py
srb/assets/robot/mobile_manipulation/combined.py
srb/assets/robot/mobile_manipulation/generic_humanoid.py
srb/assets/robot/mobile_manipulation/unitree.py
srb/assets/scenery/__init__.py
srb-0.0.5.dist-info/METADATA
srb-0.0.5.dist-info/WHEEL
srb-0.0.5.dist-info/entry_points.txt
srb-0.0.5.dist-info/licenses/LICENSE-APACHE
srb-0.0.5.dist-info/licenses/LICENSE-MIT
srb-0.0.5.dist-info/RECORD
